cputools/__init__.py
cputools/__main__.py
cputools/cputools.py
py_cputools-0.0.10.dist-info/LICENSE
py_cputools-0.0.10.dist-info/METADATA
py_cputools-0.0.10.dist-info/WHEEL
py_cputools-0.0.10.dist-info/entry_points.txt
py_cputools-0.0.10.dist-info/top_level.txt
py_cputools-0.0.10.dist-info/RECORD
