Metadata-Version: 2.1
Name: py-cputools
Version: 0.0.10
Summary: Py-cputools is used by container apps to for CPU control/query
Author-email: Jianzhu Zhang <jianzhan@gmail.com>
Maintainer-email: Jianzhu Zhang <jianzhan@gmail.com>
License: MIT License
Project-URL: Homepage, https://github.com/jianzzha/py-cputools
Project-URL: Bug Reports, https://github.com/jianzzha/py-cputools/issues
Project-URL: Source, https://github.com/jianzzha/py-cputools/
Keywords: container,cpu
Classifier: Development Status :: 3 - Alpha
Classifier: Intended Audience :: Developers
Classifier: Topic :: Software Development :: Libraries :: Python Modules
Classifier: License :: OSI Approved :: MIT License
Classifier: Programming Language :: Python :: 3
Classifier: Programming Language :: Python :: 3.6
Classifier: Programming Language :: Python :: 3.7
Classifier: Programming Language :: Python :: 3.8
Classifier: Programming Language :: Python :: 3.9
Classifier: Programming Language :: Python :: 3.10
Classifier: Programming Language :: Python :: 3.11
Classifier: Programming Language :: Python :: 3 :: Only
Requires-Python: >=3.6
License-File: LICENSE
